pdkf/__init__.py
pdkf/pdkf.py
pdkf-1.1.0.dist-info/LICENSE
pdkf-1.1.0.dist-info/METADATA
pdkf-1.1.0.dist-info/WHEEL
pdkf-1.1.0.dist-info/top_level.txt
pdkf-1.1.0.dist-info/RECORD
