Metadata-Version: 2.1
Name: pdkf
Version: 1.1.0
Summary: Module for working with PDKF files and Pandas dataframes
Home-page: https://github.com/KerrLiGit/pdkf
Author: KerrLi
Author-email: bogatyreva_aa@mail.ru
Project-URL: Documentation, https://github.com/KerrLiGit/pdkf/wiki
Keywords: pdkf
Classifier: Programming Language :: Python :: 3.11
Classifier: License :: OSI Approved :: MIT License
Classifier: Operating System :: OS Independent
Requires-Python: >=3.7
License-File: LICENSE
Requires-Dist: pandas (>=2.1.0)
Requires-Dist: zipp (>=3.17.0)
